pytobase/__init__.py
pytobase/__main__.py
pytobase/encode.py
pytobase/pytobase/__init__.py
pytobase/pytobase/__main__.py
pytobase-0.0.2.dist-info/METADATA
pytobase-0.0.2.dist-info/WHEEL
pytobase-0.0.2.dist-info/top_level.txt
pytobase-0.0.2.dist-info/RECORD
