Metadata-Version: 2.2
Name: pytobase
Version: 0.0.2
Summary: This module will help you encrypt a python file using base64 encoding
Author: Zailox
Author-email: zailox@mail.ru
Keywords: files speedfiles
Classifier: Programming Language :: Python :: 3.11
Classifier: License :: OSI Approved :: MIT License
Classifier: Operating System :: OS Independent
Requires-Python: >=3.6
Dynamic: author
Dynamic: author-email
Dynamic: classifier
Dynamic: description
Dynamic: description-content-type
Dynamic: keywords
Dynamic: requires-python
Dynamic: summary
